{
  "image_path": "/Users/angelowashington/Lavish_bot/lavish_core/data/images_in/IMG_2078.PNG",
  "cache_key": "668a93ac0d1a5b5c9241ab19b8ce2c231102d9ba",
  "preproc": [
    "gray",
    "denoise",
    "athr",
    "deskew:-90.0deg"
  ],
  "ocr_text": "10:39 a) 5G+ @ ) < Posts thestockalley AMD AMD $221.96 @ A $10.45 (4.94%) Today 24 Hour Market O23 Q5 V3 W thestockalley My AMD trade on Patreon paying today ¢) ¢ 16 hours ago G&% thestockalley A $28.60 (8.33%) Past week @ 8",
  "parsed": {},
  "duration_sec": 6.434
}